README.md
setup.cfg
setup.py
merakiv2/__init__.py
merakiv2/meraki.py
merakiv2.egg-info/PKG-INFO
merakiv2.egg-info/SOURCES.txt
merakiv2.egg-info/dependency_links.txt
merakiv2.egg-info/requires.txt
merakiv2.egg-info/top_level.txt