Metadata-Version: 1.1
Name: merakiv2
Version: 2.0
Summary: updated python library for use with dashboard. original python api made by Shiyue Cheng
Home-page: https://github.com/nielsvanhooy/dashboard-api-python
Author: hooij804
Author-email: nielsvanhooy@gmail.com
License: MIT
Download-URL: https://github.com/nielsvanhooy/dashboard-api-python/archive/v2.0.tar.gz
Keywords: Meraki,SD-WAN,Meraki API
Platform: UNKNOWN
